metta/__init__.py
metta/datafiles.py
metta/metta_io.py
metta/upload_s3.py
metta_data-1.0.0.dist-info/DESCRIPTION.rst
metta_data-1.0.0.dist-info/METADATA
metta_data-1.0.0.dist-info/RECORD
metta_data-1.0.0.dist-info/WHEEL
metta_data-1.0.0.dist-info/metadata.json
metta_data-1.0.0.dist-info/top_level.txt
