Metadata-Version: 2.0
Name: metta-data
Version: 1.0.0
Summary: Store/Read train and test matrices
Home-page: https://github.com/dssg/metta-data
Author: Center for Data Science and Public Policy
Author-email: datascifellows@gmail.com
License: BY DOWNLOADING metta-data PROGRAM YOU AGREE TO THE FOLLOWING TERMS OF USE:
Requires-Dist: PyYAML
Requires-Dist: boto3
Requires-Dist: numpy
Requires-Dist: pandas
Requires-Dist: python-dateutil
Requires-Dist: tables
